NEWS.txt
README.txt
ez_setup.py
loop-run.cmd
setup.cfg
setup.py
cogen/__init__.py
cogen/common.py
cogen.egg-info/PKG-INFO
cogen.egg-info/SOURCES.txt
cogen.egg-info/dependency_links.txt
cogen.egg-info/entry_points.txt
cogen.egg-info/top_level.txt
cogen.egg-info/zip-safe
cogen/core/__init__.py
cogen/core/coroutines.py
cogen/core/events.py
cogen/core/pipe.py
cogen/core/pubsub.py
cogen/core/queue.py
cogen/core/schedulers.py
cogen/core/sockets.py
cogen/core/util.py
cogen/core/proactors/__init__.py
cogen/core/proactors/base.py
cogen/core/proactors/epoll_impl.py
cogen/core/proactors/iocp_impl.py
cogen/core/proactors/kqueue_impl.py
cogen/core/proactors/poll_impl.py
cogen/core/proactors/select_impl.py
cogen/core/proactors/stdlib_epoll_impl.py
cogen/core/proactors/stdlib_kqueue_impl.py
cogen/core/proactors/ctypes_iocp_impl/__init__.py
cogen/core/proactors/ctypes_iocp_impl/api_consts.py
cogen/core/proactors/ctypes_iocp_impl/api_wrappers.py
cogen/web/__init__.py
cogen/web/async.py
cogen/web/wsgi.py
docs/conf.py
docs/index.rst
docs/_templates/layout.html
docs/build/genindex.html
docs/build/index.html
docs/build/modindex.html
docs/build/objects.inv
docs/build/search.html
docs/build/searchindex.js
docs/build/_static/contents.png
docs/build/_static/default.css
docs/build/_static/doctools.js
docs/build/_static/file.png
docs/build/_static/jquery.js
docs/build/_static/minus.png
docs/build/_static/navigation.png
docs/build/_static/plus.png
docs/build/_static/pygments.css
docs/build/_static/rightsidebar.css
docs/build/_static/searchtools.js
docs/build/_static/sphinxdoc.css
docs/build/_static/stickysidebar.css
docs/build/_static/traditional.css
docs/build/intro/install.html
docs/build/intro/introduction.html
docs/build/modules/cogen.core.coroutines.html
docs/build/modules/cogen.core.events.html
docs/build/modules/cogen.core.html
docs/build/modules/cogen.core.pipe.html
docs/build/modules/cogen.core.proactors.base.html
docs/build/modules/cogen.core.proactors.html
docs/build/modules/cogen.core.proactors.select_impl.html
docs/build/modules/cogen.core.pubsub.html
docs/build/modules/cogen.core.queue.html
docs/build/modules/cogen.core.schedulers.html
